{"config": {"view": {"continuousWidth": 300, "continuousHeight": 300}}, "data": {"name": "data-c861b5406b3bcc0af23e13047c57c4c6"}, "mark": {"type": "bar"}, "encoding": {"tooltip": [{"field": "Citt\u00e0", "type": "nominal"}, {"field": "Count", "type": "quantitative"}], "x": {"field": "Count", "title": "Numero Lead", "type": "quantitative"}, "y": {"field": "Citt\u00e0", "sort": "-x", "title": "Citt\u00e0", "type": "nominal"}}, "title": "Top 10 Citt\u00e0 per Volume Lead - Franchising", "$schema": "https://vega.github.io/schema/vega-lite/v5.20.1.json", "datasets": {"data-c861b5406b3bcc0af23e13047c57c4c6": [{"Citt\u00e0": "Roma", "Count": 28}, {"Citt\u00e0": "Napoli", "Count": 21}, {"Citt\u00e0": "Catania", "Count": 11}, {"Citt\u00e0": "Palermo", "Count": 9}, {"Citt\u00e0": "Salerno", "Count": 8}, {"Citt\u00e0": "Messina", "Count": 7}, {"Citt\u00e0": "Genova", "Count": 7}, {"Citt\u00e0": "Bari", "Count": 5}, {"Citt\u00e0": "Firenze", "Count": 5}, {"Citt\u00e0": "Cosenza", "Count": 4}]}}